.travis.yml
LICENSE
MANIFEST.in
README.rst
setup.cfg
setup.py
Mopidy_Party.egg-info/PKG-INFO
Mopidy_Party.egg-info/SOURCES.txt
Mopidy_Party.egg-info/dependency_links.txt
Mopidy_Party.egg-info/entry_points.txt
Mopidy_Party.egg-info/not-zip-safe
Mopidy_Party.egg-info/requires.txt
Mopidy_Party.egg-info/top_level.txt
mopidy_party/__init__.py
mopidy_party/ext.conf
mopidy_party/static/controller.js
mopidy_party/static/dark.css
mopidy_party/static/index.html
mopidy_party/static/original.css
mopidy_party/static/vendors/angular.min.js
mopidy_party/static/vendors/bootstrap.min.css
mopidy_party/static/vendors/mopidy.min.js
mopidy_party/static/vendors/fontawesome/css/all.min.css
mopidy_party/static/vendors/fontawesome/webfonts/fa-brands-400.woff2
mopidy_party/static/vendors/fontawesome/webfonts/fa-regular-400.woff2
mopidy_party/static/vendors/fontawesome/webfonts/fa-solid-900.woff2
mopidy_party/static/vendors/fontawesome/webfonts/fa-v4compatibility.woff2