Metadata-Version: 2.1
Name: Mopidy-Party
Version: 1.3.0
Summary: Mopidy web extension designed for party
Home-page: https://github.com/Lesterpig/mopidy-party
Author: Loick Bonniot
Author-email: pip@lesterpig.com
License: Apache License, Version 2.0
Classifier: Environment :: No Input/Output (Daemon)
Classifier: Intended Audience :: End Users/Desktop
Classifier: License :: OSI Approved :: Apache Software License
Classifier: Operating System :: OS Independent
Classifier: Programming Language :: Python :: 3
Classifier: Topic :: Multimedia :: Sound/Audio :: Players
License-File: LICENSE
